connectors_to_databases/BaseOperator.py
connectors_to_databases/ClickHouse.py
connectors_to_databases/MSSQL.py
connectors_to_databases/MariaDB.py
connectors_to_databases/MySQL.py
connectors_to_databases/PostgreSQL.py
connectors_to_databases/TypeHinting.py
connectors_to_databases/__init__.py
connectors_to_databases/helper_functions/function_list.py
connectors_to_databases-1.1.8.dist-info/LICENSE.MD
connectors_to_databases-1.1.8.dist-info/METADATA
connectors_to_databases-1.1.8.dist-info/WHEEL
connectors_to_databases-1.1.8.dist-info/RECORD
