Metadata-Version: 2.1
Name: connectors-to-databases
Version: 1.1.8
Summary: Python module for connect with DataBases
License: Apache License
Author: Ivan Korsakov
Author-email: korsakov.iyu@gmail.com
Requires-Python: >=3.11.1,<4.0.0
Classifier: License :: Other/Proprietary License
Classifier: Programming Language :: Python :: 3
Classifier: Programming Language :: Python :: 3.12
Requires-Dist: clickhouse-connect (>=0.7.18,<0.8.0)
Requires-Dist: cryptography (==43.0.0)
Requires-Dist: numpy (==1.26.4)
Requires-Dist: pandas (>=2.2.2,<3.0.0)
Requires-Dist: psycopg2-binary (>=2.9.9,<3.0.0)
Requires-Dist: pymysql (>=1.1.1,<2.0.0)
Requires-Dist: sqlalchemy (>=2.0.32,<3.0.0)
Project-URL: Bug Tracker, https://github.com/yourusername/your-repo/issues
Project-URL: Homepage, https://github.com/yourusername/your-repo
Project-URL: PyPi, https://pypi.org/project/connectors-to-databases/
